[
  {
    "date": "Sat November 08, 2025",
    "location": "Worcester",
    "meals": {}
  },
  {
    "date": "Sun November 09, 2025",
    "location": "Worcester",
    "meals": {}
  },
  {
    "date": "Mon November 10, 2025",
    "location": "Worcester",
    "meals": {}
  },
  {
    "date": "Tue November 11, 2025",
    "location": "Worcester",
    "meals": {}
  },
  {
    "date": "Wed November 12, 2025",
    "location": "Worcester",
    "meals": {}
  },
  {
    "date": "Thu November 13, 2025",
    "location": "Worcester",
    "meals": {}
  },
  {
    "date": "Fri November 14, 2025",
    "location": "Worcester",
    "meals": {}
  },
  {
    "date": "Sat November 15, 2025",
    "location": "Worcester",
    "meals": {}
  },
  {
    "date": "Sun November 16, 2025",
    "location": "Worcester",
    "meals": {}
  },
  {
    "date": "Mon November 17, 2025",
    "location": "Worcester",
    "meals": {}
  },
  {
    "date": "Tue November 18, 2025",
    "location": "Worcester",
    "meals": {}
  },
  {
    "date": "Wed November 19, 2025",
    "location": "Worcester",
    "meals": {}
  },
  {
    "date": "Thu November 20, 2025",
    "location": "Worcester",
    "meals": {}
  },
  {
    "date": "Fri November 21, 2025",
    "location": "Worcester",
    "meals": {}
  }
]